notifications/__init__.py
notifications/admin.py
notifications/apps.py
notifications/choices.py
notifications/consumers.py
notifications/managers.py
notifications/models.py
notifications/paginations.py
notifications/routing.py
notifications/serializers.py
notifications/services.py
notifications/signals.py
notifications/urls.py
notifications/views.py
notifications/management/__init__.py
notifications/management/commands/__init__.py
notifications/management/commands/init_notification_settings.py
notifications/middleware/__init__.py
notifications/middleware/current_user_middleware.py
notifications/middleware/jwt_middleware.py
notifications/migrations/0001_initial.py
notifications/migrations/__init__.py
notifications/tests/__init__.py
notifications/tests/base_test.py
notifications/tests/payloads.py
notifications/tests/test_helpers.py
notifications/tests/test_http_api.py
notifications/tests/test_websocket_api.py
notifications/tests/urlhelpers.py
notifications/utils/__init__.py
notifications/utils/cache.py
notifications/utils/consumers.py
notifications/utils/current_user.py
notifications/utils/notifications.py
notifications/utils/schema_validations.py
django_notifications_websocket-2.0.1.dist-info/LICENSE
django_notifications_websocket-2.0.1.dist-info/METADATA
django_notifications_websocket-2.0.1.dist-info/WHEEL
django_notifications_websocket-2.0.1.dist-info/top_level.txt
django_notifications_websocket-2.0.1.dist-info/RECORD
