Metadata-Version: 2.2
Name: django-notifications-websocket
Version: 2.0.1
Summary: A Django app for real-time notifications using WebSocket.
Home-page: https://github.com/JOYBARMAN/django-notifications-websocket
Author: JOY BARMAN
Author-email: barmanjoy88@gmail.com
License: MIT
Classifier: Framework :: Django
Classifier: Programming Language :: Python :: 3
Classifier: License :: OSI Approved :: MIT License
Classifier: Operating System :: OS Independent
Requires-Python: >=3.8
License-File: LICENSE
Requires-Dist: channels[daphne]
Requires-Dist: jsonschema
Requires-Dist: channels-redis
Dynamic: author
Dynamic: author-email
Dynamic: classifier
Dynamic: description
Dynamic: description-content-type
Dynamic: home-page
Dynamic: license
Dynamic: requires-dist
Dynamic: requires-python
Dynamic: summary
